[
  {
    "path": "كم عدد سور القرآن الكريم؟",
    "q1": "111",
    "q2": "112",
    "q3": "113",
    "q4": "114",
    "filename": "114"
  },
  {
    "path": "في أي الأيام خلق سيدنا آدم عليه السلام؟",
    "q1": "السبت",
    "q2": "الجمعة",
    "q3": "الخميس",
    "q4": "الأحد",
    "filename": "الجمعة"
  },
  {
    "path": "كم عدد السنوات التي نام فيها أهل الكهف؟",
    "q1": "300",
    "q2": "309",
    "q3": "400",
    "q4": "409",
    "filename": "309"
  },
  {
    "path": "سورة قصيرة من قرأها ثلاثا فكأنما قرأ كل القرآن؟",
    "q1": "الناس",
    "q2": "الإخلاص",
    "q3": "الفلق",
    "q4": "",
    "filename": "الإخلاص"
  },
  {
    "path": "من هو النبي الذي كانت إحدى معجزاته العصا التي تتحول إلى حية تسعى؟",
    "q1": "موسى",
    "q2": "عيسى",
    "q3": "إسحاق",
    "q4": "",
    "filename": "موسى"
  },
  {
    "path": "من هو النبي الملقب بالذبيح؟",
    "q1": "إسماعيل",
    "q2": "إبراهيم",
    "q3": "إسحاق",
    "q4": "",
    "filename": "إسماعيل"
  },
  {
    "path": "من هو النبي الذي أُرسل إلى قوم ثمود؟",
    "q1": "صالح",
    "q2": "هود",
    "q3": "نوح",
    "q4": "",
    "filename": "صالح"
  },
  {
    "path": "الشهر الثامن في التقويم الهجري؟",
    "q1": "شعبان",
    "q2": "محرم",
    "q3": "شوال",
    "q4": "",
    "filename": "شعبان"
  },
  {
    "path": "كم عدد آيات سورة البقرة؟",
    "q1": "286",
    "q2": "280",
    "q3": "277",
    "q4": "",
    "filename": "286"
  },
  {
    "path": "كم عدد القراءات الصحيحة للقرآن الكريم؟",
    "q1": "10",
    "q2": "8",
    "q3": "9",
    "q4": "",
    "filename": "10"
  },
  {
    "path": "من أول من لُقب بأمير المؤمنين؟",
    "q1": "عمر (بن عفان)",
    "q2": "خالد (بن الوليد)",
    "q3": "عمر (بن الخطاب)",
    "q4": "",
    "filename": "عمر"
  },
  {
    "path": "ما آخر سورة نزلت في مكة؟",
    "q1": "النصر",
    "q2": "القارعة",
    "q3": "المرسلات",
    "q4": "",
    "filename": "المرسلات"
  },
  {
    "path": "كم عدد السور التي ابتدأت بالحروف المقطعة (الم)؟",
    "q1": "6",
    "q2": "5",
    "q3": "4",
    "q4": "",
    "filename": "6"
  },
  {
    "path": "أين ذكرت الآية الكريمة: (وما آتاكم الرسول فخذوه وما نهاكم عنه فانتهوا)؟",
    "q1": "الحشر",
    "q2": "الصف",
    "q3": "الجمعة",
    "q4": "",
    "filename": "الحشر"
  },
  {
    "path": "من هو النبي الذي دعا ربه (توفني مسلما وألحقني بالصالحين)؟",
    "q1": "يوسف",
    "q2": "صالح",
    "q3": "إبراهيم",
    "q4": "",
    "filename": "يوسف"
  },
  {
    "path": "في أي سورة وردت الآية التالية (ولبثوا في كهفهم ثلاث مئة سنين وازدادوا تسعا)؟",
    "q1": "الكهف",
    "q2": "فصلت",
    "q3": "مريم",
    "q4": "",
    "filename": "الكهف"
  },
  {
    "path": "ما هي أطول سورة في القرآن الكريم؟",
    "q1": "البقرة",
    "q2": "آل عمران",
    "q3": "النساء",
    "q4": "",
    "filename": "البقرة"
  },
  {
    "path": "من هو ثاني نبي من بعد نبي آدم عليه السلام؟",
    "q1": "نوح",
    "q2": "إبراهيم",
    "q3": "إدريس",
    "q4": "شيث",
    "filename": "شيث"
  },
  {
    "path": "ما هي السورة التي تسمى سورة التوديع؟",
    "q1": "الحج",
    "q2": "النصر",
    "q3": "الفيل",
    "q4": "",
    "filename": "النصر"
  },
  {
    "path": "كم عدد السور التي افتتحت بثلاثة أحرف؟",
    "q1": "13",
    "q2": "14",
    "q3": "16",
    "q4": "",
    "filename": "13"
  },
  {
    "path": "من أسماء الخيل التي ذكرت في القرآن الكريم؟",
    "q1": "النازعات",
    "q2": "الذاريات",
    "q3": "العاديات",
    "q4": "",
    "filename": "العاديات"
  },
  {
    "path": "كم مرة ذكرت السيدة مريم في القرآن الكريم؟",
    "q1": "34",
    "q2": "42",
    "q3": "43",
    "q4": "",
    "filename": "34"
  },
  {
    "path": "ما اسم السورة التي تنتهي آياتها بحرف السين؟",
    "q1": "الضحى",
    "q2": "الناس",
    "q3": "الصمد",
    "q4": "",
    "filename": "الناس"
  },
  {
    "path": "ما هو عدد حملة العرش يوم القيامة والمذكورين في القرآن الكريم؟",
    "q1": "6",
    "q2": "8",
    "q3": "9",
    "q4": "",
    "filename": "8"
  },
  {
    "path": "ما هي السورة التي يطلق عليها أم الكتاب؟",
    "q1": "الفاتحة",
    "q2": "يس",
    "q3": "البقرة",
    "q4": "",
    "filename": "الفاتحة"
  },
  {
    "path": "من هو الصحابي الجليل الذي كان مُلقباً بـأسد الله الغالب؟",
    "q1": "علي",
    "q2": "عمر",
    "q3": "زيد",
    "q4": "",
    "filename": "علي"
  },
  {
    "path": "من هو النبي الذي تم تكليفه بقتل المسيح الدجال؟",
    "q1": "عيسى",
    "q2": "نوح",
    "q3": "آدم",
    "q4": "",
    "filename": "عيسى"
  },
  {
    "path": "من هو النبي الذي له لقب أبو الأنبياء؟",
    "q1": "إبراهيم",
    "q2": "آدم",
    "q3": "نوح",
    "q4": "",
    "filename": "إبراهيم"
  },
  {
    "path": "من هو أول نبي يقوم بقرع باب الجنة يوم القيامة؟",
    "q1": "محمد",
    "q2": "إبراهيم",
    "q3": "يوسف",
    "q4": "",
    "filename": "محمد"
  },
  {
    "path": "من هو شيخ المُرسلين من الأنبياء؟",
    "q1": "نوح",
    "q2": "موسى",
    "q3": "إبراهيم",
    "q4": "",
    "filename": "نوح"
  },
  {
    "path": "بماذا لقب إبراهيم عليه السلام؟",
    "q1": "الخليل",
    "q2": "الصديق",
    "q3": "إسرائيل",
    "q4": "",
    "filename": "الخليل"
  },
  {
    "path": "كم كان عمر الرسول صلى الله عليه وسلم عندما بُعث؟",
    "q1": "40",
    "q2": "50",
    "q3": "30",
    "q4": "",
    "filename": "40"
  },
  {
    "path": "ما هو العام الهجري الذي احتفل فيه المسلمين بعيد الفطر وعيد الأضحى المبارك؟",
    "q1": "الثاني",
    "q2": "الأول",
    "q3": "الثالث",
    "q4": "",
    "filename": "الثاني"
  },
  {
    "path": "ما هي السورة التي لا تحتوي على حرف الميم؟",
    "q1": "التوبة",
    "q2": "الكوثر",
    "q3": "النصر",
    "q4": "الفيل",
    "filename": "الكوثر"
  },
  {
    "path": "كم كان عمر النبي صلى الله عليه وسلم حين وفاة زوجته خديجة بنت خويلد رضى الله عنها؟",
    "q1": "51",
    "q2": "45",
    "q3": "48",
    "q4": "53",
    "filename": "51"
  },
  {
    "path": "كم عدد التكبيرات في الركعة الأولى في صلاة العيد؟",
    "q1": "7",
    "q2": "8",
    "q3": "9",
    "q4": "",
    "filename": "7"
  },
  {
    "path": "من هو أول من أسلم من النساء؟",
    "q1": "خديجة بنت خويلد",
    "q2": "فاطمة بنت محمد",
    "q3": "عائشة بنت أبي بكر",
    "q4": "",
    "filename": "خديجة بنت خويلد"
  },
  {
    "path": "كم عدد ركعات صلاة الفجر؟",
    "q1": "2",
    "q2": "4",
    "q3": "6",
    "q4": "",
    "filename": "2"
  },
  {
    "path": "من هو والد النبي إبراهيم؟",
    "q1": "آزر",
    "q2": "هارون",
    "q3": "يعقوب",
    "q4": "",
    "filename": "آزر"
  }
]
